{
  "photo_info_dto_list": [
    {
      "photo_id": 5,
      "img_url": "https://nonghaeng.s3.ap-northeast-2.amazonaws.com/experiences/image_1715321340377_5798ce40-eb02-4fd5-98e3-e20bd55d87cf.jpeg",
      "representative": true
    },
    {
      "photo_id": 6,
      "img_url": "https://nonghaeng.s3.ap-northeast-2.amazonaws.com/experiences/image_1715321341447_8f739ba3-3ee1-4a32-a626-a5cb60582794.jpeg",
      "representative": false
    }
  ],
  "experience_name": "소타기 체험",
  "experience_type_name": "만들기체험",
  "start_date": "2024-01-01",
  "end_date": "2024-12-31",
  "min_participant": 2,
  "max_participant": 30,
  "price": 9000,
  "duration_hours": 3,
  "check_point": "1.소타기 체험. 2.남녀노소 가능",
  "detail_introduction": "소타셈 . 재밌어요. 말보다 나음",
  "summary": "소 타보슈",
  "supplies": "없음.",
  "precautions": "소 타다가 다치면 책임 못집니다.",
  "likes": 1,
  "tour_info": {
    "tourId": 4,
    "tourName": "창민체험휴양마을",
    "areaName": "대전"
  },
  "seller_info": {
    "address": "대전광역시 유성구 노은로 353,301-1701",
    "callNumber": "041-1234-1234"
  }
}
